LeetCode_problem_info/__init__.py
LeetCode_problem_info/problem_info.py
LeetCode_problem_info-0.1.2.dist-info/LICENSE
LeetCode_problem_info-0.1.2.dist-info/METADATA
LeetCode_problem_info-0.1.2.dist-info/WHEEL
LeetCode_problem_info-0.1.2.dist-info/top_level.txt
LeetCode_problem_info-0.1.2.dist-info/RECORD
