Metadata-Version: 2.1
Name: LeetCode-problem-info
Version: 0.1.2
Summary: A python package to get metadata of LeetCode problems
Home-page: https://github.com/Mo-Shakib/Leetcode-python-package
Author: Mohammad Shakib
Author-email: mo.shakib.official@gmail.com
License: UNKNOWN
Project-URL: Bug Tracker, https://github.com/Mo-Shakib/Leetcode-python-package/issues
Platform: UNKNOWN
Classifier: Programming Language :: Python :: 3
Classifier: License :: OSI Approved :: MIT License
Classifier: Operating System :: OS Independent
Requires-Python: >=3.6
License-File: LICENSE
